quik_python/__init__.py
quik_python/events.py
quik_python/exceptions.py
quik_python/misc.py
quik_python/quik.py
quik_python/quik_service.py
quik_python/storage.py
quik_python/data_structures/__init__.py
quik_python/data_structures/account_balance.py
quik_python/data_structures/account_position.py
quik_python/data_structures/all_trade.py
quik_python/data_structures/base.py
quik_python/data_structures/buy_sell_info.py
quik_python/data_structures/calc_buy_sell_result.py
quik_python/data_structures/candle.py
quik_python/data_structures/class_info.py
quik_python/data_structures/depo_limit.py
quik_python/data_structures/depo_limit_delete.py
quik_python/data_structures/depo_limit_ex.py
quik_python/data_structures/event_names.py
quik_python/data_structures/firm.py
quik_python/data_structures/futures_client_holding.py
quik_python/data_structures/futures_limit_delete.py
quik_python/data_structures/futures_limits.py
quik_python/data_structures/info_params.py
quik_python/data_structures/label.py
quik_python/data_structures/money_limit.py
quik_python/data_structures/money_limit_delete.py
quik_python/data_structures/money_limit_ex.py
quik_python/data_structures/option_board.py
quik_python/data_structures/order.py
quik_python/data_structures/order_book.py
quik_python/data_structures/param.py
quik_python/data_structures/param_names.py
quik_python/data_structures/param_table.py
quik_python/data_structures/portfolio_info.py
quik_python/data_structures/portfolio_info_ex.py
quik_python/data_structures/quik_datetime.py
quik_python/data_structures/quik_table.py
quik_python/data_structures/security_info.py
quik_python/data_structures/stop_order.py
quik_python/data_structures/trade.py
quik_python/data_structures/trade_accounts.py
quik_python/data_structures/transaction.py
quik_python/data_structures/transaction_reply.py
quik_python/data_structures/transaction_types.py
quik_python/functions/__init__.py
quik_python/functions/base_functions.py
quik_python/functions/candle_functions.py
quik_python-1.2.0.dist-info/METADATA
quik_python-1.2.0.dist-info/WHEEL
quik_python-1.2.0.dist-info/entry_points.txt
quik_python-1.2.0.dist-info/licenses/AUTHORS.md
quik_python-1.2.0.dist-info/licenses/LICENSE
quik_python-1.2.0.dist-info/RECORD
