Metadata-Version: 2.4
Name: quik-python
Version: 1.2.0
Summary: Python interface for QUIK trading terminal
Project-URL: Homepage, https://github.com/Alex-Shur/quik_python
Project-URL: Source, https://github.com/Alex-Shur/quik_python
Author: LEX
License: Apache-2.0
License-File: AUTHORS.md
License-File: LICENSE
Classifier: Development Status :: 5 - Production/Stable
Classifier: License :: OSI Approved :: Apache Software License
Classifier: Operating System :: OS Independent
Classifier: Programming Language :: Python :: 3
Requires-Python: >=3.11
Requires-Dist: asyncio
Provides-Extra: dev
Requires-Dist: pytest-asyncio>=0.21.0; extra == 'dev'
Requires-Dist: pytest>=7.0.0; extra == 'dev'
Provides-Extra: test
Requires-Dist: pytest-asyncio>=0.21.0; extra == 'test'
Requires-Dist: pytest>=7.0.0; extra == 'test'
